micromegas/__init__.py
micromegas/admin.py
micromegas/auth/__init__.py
micromegas/auth/oidc.py
micromegas/flightsql/FlightSql_pb2.py
micromegas/flightsql/__init__.py
micromegas/flightsql/client.py
micromegas/flightsql/time.py
micromegas/oidc_connection.py
micromegas/perfetto.py
micromegas/time.py
micromegas-0.18.0.dist-info/METADATA
micromegas-0.18.0.dist-info/WHEEL
micromegas-0.18.0.dist-info/entry_points.txt
micromegas-0.18.0.dist-info/RECORD
