Metadata-Version: 2.3
Name: micromegas
Version: 0.18.0
Summary: Python analytics client for https://github.com/madesroches/micromegas/
Author: Marc-Antoine Desroches
Author-email: madesroches@gmail.com
Requires-Python: >=3.10,<4.0
Classifier: Programming Language :: Python :: 3
Classifier: Programming Language :: Python :: 3.10
Classifier: Programming Language :: Python :: 3.11
Classifier: Programming Language :: Python :: 3.12
Classifier: Programming Language :: Python :: 3.13
Requires-Dist: authlib (>=1.3.0,<2.0.0)
Requires-Dist: certifi (>=2025.4.26,<2026.0.0)
Requires-Dist: grpcio (>=1.69.0,<2.0.0)
Requires-Dist: numpy (>=2.2.6,<3.0.0)
Requires-Dist: pandas (>=2.2.2,<3.0.0)
Requires-Dist: protobuf (>=5.29.0,<6.0.0)
Requires-Dist: pyarrow (>=20.0.0,<21.0.0)
Requires-Dist: requests (>=2.32.0,<3.0.0)
Requires-Dist: tabulate (>=0.9.0,<0.10.0)
Requires-Dist: tqdm (>=4.66.0,<5.0.0)
